smart_gestures/__init__.py
smart_gestures/alphabet/__init__.py
smart_gestures/alphabet/asl_model/__init__.py
smart_gestures/alphabet/asl_model/model.py
smart_gestures/alphabet/vgt_model/__init__.py
smart_gestures/alphabet/vgt_model/model.py
smart_gestures/gestures/lstm_model/data_utils.py
smart_gestures/gestures/lstm_model/label_utils.py
smart_gestures-0.2.2.dist-info/licenses/LICENSE
smart_gestures-0.2.2.dist-info/METADATA
smart_gestures-0.2.2.dist-info/WHEEL
smart_gestures-0.2.2.dist-info/top_level.txt
smart_gestures-0.2.2.dist-info/RECORD
