Metadata-Version: 2.4
Name: smart_gestures
Version: 0.2.2
Summary: Utilities and models for ASL alphabet training used in the SmartGlasses project
Author: Simon Stijnen, Lynn Delaere, Olivier Westerman
Maintainer: VIVES University of Applied Sciences - Project XP
License: GPL-3.0-or-later
Project-URL: Homepage, https://github.com/vives-project-xp/SmartGlasses/tree/main/notebooks/package
Project-URL: Repository, https://github.com/vives-project-xp/SmartGlasses
Project-URL: Issues, https://github.com/vives-project-xp/SmartGlasses/issues
Classifier: Programming Language :: Python :: 3
Classifier: Programming Language :: Python :: 3.12
Classifier: License :: OSI Approved :: GNU General Public License v3 or later (GPLv3+)
Classifier: Operating System :: OS Independent
Classifier: Development Status :: 4 - Beta
Classifier: Intended Audience :: Developers
Classifier: Intended Audience :: Science/Research
Classifier: Topic :: Scientific/Engineering :: Artificial Intelligence
Classifier: Topic :: Software Development :: Libraries :: Python Modules
Requires-Python: <3.13,>=3.9
License-File: LICENSE
Requires-Dist: mediapipe==0.10.21
Requires-Dist: numpy==1.26.4
Requires-Dist: pandas==2.3.3
Requires-Dist: torch==2.7.0
Requires-Dist: tqdm==4.67.1
Dynamic: license-file
